<?xml version="1.0" encoding="utf-8"?>
<abapGit version="v1.0.0" serializer="LCL_OBJECT_W3MI" serializer_version="v2.0.0">
 <asx:abap xmlns:asx="http://www.sap.com/abapxml" version="1.0">
  <asx:values>
   <NAME>ZDEMO_EXCEL45</NAME>
   <TEXT>45_ShowDropdown.xlsx (ZDEMO_EXCEL45)</TEXT>
   <PARAMS>
    <WWWPARAMS>
     <RELID>MI</RELID>
     <OBJID>ZDEMO_EXCEL45</OBJID>
     <NAME>fileextension</NAME>
     <VALUE>.xlsx</VALUE>
    </WWWPARAMS>
    <WWWPARAMS>
     <RELID>MI</RELID>
     <OBJID>ZDEMO_EXCEL45</OBJID>
     <NAME>filename</NAME>
     <VALUE>45_ShowDropdown.xlsx</VALUE>
    </WWWPARAMS>
    <WWWPARAMS>
     <RELID>MI</RELID>
     <OBJID>ZDEMO_EXCEL45</OBJID>
     <NAME>mimetype</NAME>
     <VALUE>application/vnd.openxmlformats-officedocument.spreadsheetml.sheet</VALUE>
    </WWWPARAMS>
   </PARAMS>
  </asx:values>
 </asx:abap>
</abapGit>
